intentron/__init__.py
intentron/__main__.py
intentron/main.py
intentron/stages/__init__.py
intentron/stages/check_stage.py
intentron/stages/crop_stage.py
intentron/stages/draw.py
intentron/stages/estimate.py
intentron/stages/fuse_stage.py
intentron/stages/gather_stage.py
intentron/stages/infer.py
intentron/stages/load_stage.py
intentron/stages/parse_stage.py
intentron/stages/pipeline_stage.py
intentron/stages/pretty.py
intentron/stages/separate_stage.py
intentron/utils/__init__.py
intentron/utils/fmt.py
intentron/utils/io.py
intentron/utils/utils.py
intentron-0.1.9.dist-info/WHEEL
intentron-0.1.9.dist-info/METADATA
intentron-0.1.9.dist-info/RECORD
