Metadata-Version: 2.1
Name: intentron
Version: 0.1.9
Summary: 
Author: catsudo
Author-email: catsudo@nous.dev
Requires-Python: >=3.7,<3.10
Classifier: Programming Language :: Python :: 3
Classifier: Programming Language :: Python :: 3.7
Classifier: Programming Language :: Python :: 3.8
Classifier: Programming Language :: Python :: 3.9
Requires-Dist: alive-progress (>=2.4.1,<3.0.0)
Requires-Dist: click (>=8.1.3,<9.0.0)
Requires-Dist: loguru (>=0.6.0,<0.7.0)
Requires-Dist: matplotlib (>=3.5.2,<4.0.0)
Requires-Dist: mediapipe (>=0.8)
Requires-Dist: opencv-python (>=4.5.5,<5.0.0)
Requires-Dist: pandas (>=1.4.2,<2.0.0)
Requires-Dist: scikit-learn (>=1.1.1,<2.0.0)
Requires-Dist: scipy (>=1.8.1,<2.0.0)
Requires-Dist: seaborn (>=0.11.2,<0.12.0)
